modelred/__init__.py
modelred/_common.py
modelred/aclient.py
modelred/client.py
modelred/errors.py
modelred-0.1.40.dist-info/METADATA
modelred-0.1.40.dist-info/WHEEL
modelred-0.1.40.dist-info/entry_points.txt
modelred-0.1.40.dist-info/RECORD
