Metadata-Version: 2.4
Name: modelred
Version: 0.1.40
Summary: ModelRed SDK - Python
Project-URL: Homepage, https://modelred.ai
Project-URL: Documentation, https://modelred.ai/docs
Author-email: ModelRed AI <contact@modelred.ai>
Requires-Python: >=3.6
Requires-Dist: aiohttp>=3.8.6
Requires-Dist: httpx>=0.20.0
Requires-Dist: requests>=2.25.0
